sciprs-0.1.2.dist-info/METADATA
sciprs-0.1.2.dist-info/WHEEL
sciprs/__init__.py
sciprs/sciprs.cpython-39-x86_64-linux-gnu.so
sciprs-0.1.2.dist-info/RECORD
